{
  "id": "Pojav",
  "name": "Pojav调整布局",
  "version": "1.0.0",
  "versionCode": 3,
  "author": "时光晓曦",
  "description": "Pojav Launcher 默认控制器的调整版。",
  "controllerVersion": 20,
  "buttonStyles": [
    {
      "name": "HY://Pojav/normal",
      "textColor": -1,
      "textSize": 12,
      "strokeColor": -16777216,
      "strokeWidth": 0,
      "cornerRadius": 0,
      "fillColor": 1291845632,
      "textColorPressed": -16777216,
      "textSizePressed": 12,
      "strokeColorPressed": -16777216,
      "strokeWidthPressed": 10,
      "cornerRadiusPressed": 0,
      "fillColorPressed": 1305267404
    }
  ],
  "directionStyles": [],
  "viewGroups": [
    {
      "id": "f5c607a6-da93-44a7-8ebc-ee75449eae58",
      "name": "NORMAL",
      "visibility": "VISIBLE",
      "viewData": {
        "buttonList": [
          {
            "id": "b8eb3df0-6e48-4fc3-b41b-3bbaeeba684c",
            "text": "Esc",
            "style": "HY://Pojav/normal",
            "baseInfo": {
              "visibilityType": "ALWAYS",
              "xPosition": 12,
              "yPosition": 8,
              "sizeType": "PERCENTAGE",
              "absoluteWidth": 50,
              "absoluteHeight": 50,
              "percentageWidth": {
                "reference": "SCREEN_HEIGHT",
                "size": 190
              },
              "percentageHeight": {
                "reference": "SCREEN_HEIGHT",
                "size": 80
              }
            },
            "event": {
              "pointerFollow": false,
              "Movable": false,
              "pressEvent": {
                "autoKeep": false,
                "autoClick": false,
                "openMenu": false,
                "switchTouchMode": false,
                "switchMouseMode": false,
                "input": false,
                "quickInput": false,
                "outputText": "",
                "outputKeycodes": [
                  1
                ],
                "bindViewGroup": []
              },
              "longPressEvent": {
                "autoKeep": false,
                "autoClick": false,
                "openMenu": false,
                "switchTouchMode": false,
                "switchMouseMode": false,
                "input": false,
                "quickInput": false,
                "outputText": "",
                "outputKeycodes": [],
                "bindViewGroup": []
              },
              "clickEvent": {
                "autoKeep": false,
                "autoClick": false,
                "openMenu": false,
                "switchTouchMode": false,
                "switchMouseMode": false,
                "input": false,
                "quickInput": false,
                "outputText": "",
                "outputKeycodes": [],
                "bindViewGroup": []
              },
              "doubleClickEvent": {
                "autoKeep": false,
                "autoClick": false,
                "openMenu": false,
                "switchTouchMode": false,
                "switchMouseMode": false,
                "input": false,
                "quickInput": false,
                "outputText": "",
                "outputKeycodes": [],
                "bindViewGroup": []
              }
            }
          },
          {
            "id": "f5845875-4ac2-441c-bc44-f9abd5063232",
            "text": "F1",
            "style": "HY://Pojav/normal",
            "baseInfo": {
              "visibilityType": "ALWAYS",
              "xPosition": 112,
              "yPosition": 8,
              "sizeType": "PERCENTAGE",
              "absoluteWidth": 50,
              "absoluteHeight": 50,
              "percentageWidth": {
                "reference": "SCREEN_HEIGHT",
                "size": 190
              },
              "percentageHeight": {
                "reference": "SCREEN_HEIGHT",
                "size": 80
              }
            },
            "event": {
              "pointerFollow": false,
              "Movable": false,
              "pressEvent": {
                "autoKeep": false,
                "autoClick": false,
                "openMenu": false,
                "switchTouchMode": false,
                "switchMouseMode": false,
                "input": false,
                "quickInput": false,
                "outputText": "",
                "outputKeycodes": [
                  1
                ],
                "bindViewGroup": []
              },
              "longPressEvent": {
                "autoKeep": false,
                "autoClick": false,
                "openMenu": false,
                "switchTouchMode": false,
                "switchMouseMode": false,
                "input": false,
                "quickInput": false,
                "outputText": "",
                "outputKeycodes": [],
                "bindViewGroup": []
              },
              "clickEvent": {
                "autoKeep": false,
                "autoClick": false,
                "openMenu": false,
                "switchTouchMode": false,
                "switchMouseMode": false,
                "input": false,
                "quickInput": false,
                "outputText": "",
                "outputKeycodes": [],
                "bindViewGroup": []
              },
              "doubleClickEvent": {
                "autoKeep": false,
                "autoClick": false,
                "openMenu": false,
                "switchTouchMode": false,
                "switchMouseMode": false,
                "input": false,
                "quickInput": false,
                "outputText": "",
                "outputKeycodes": [],
                "bindViewGroup": []
              }
            }
          },
          {
            "id": "4b71e01c-87e1-458c-b345-f36fd9760122",
            "text": "F3",
            "style": "HY://Pojav/normal",
            "baseInfo": {
              "visibilityType": "ALWAYS",
              "xPosition": 212,
              "yPosition": 8,
              "sizeType": "PERCENTAGE",
              "absoluteWidth": 50,
              "absoluteHeight": 50,
              "percentageWidth": {
                "reference": "SCREEN_HEIGHT",
                "size": 190
              },
              "percentageHeight": {
                "reference": "SCREEN_HEIGHT",
                "size": 80
              }
            },
            "event": {
              "pointerFollow": false,
              "Movable": false,
              "pressEvent": {
                "autoKeep": false,
                "autoClick": false,
                "openMenu": false,
                "switchTouchMode": false,
                "switchMouseMode": false,
                "input": false,
                "quickInput": false,
                "outputText": "",
                "outputKeycodes": [
                  61
                ],
                "bindViewGroup": []
              },
              "longPressEvent": {
                "autoKeep": false,
                "autoClick": false,
                "openMenu": false,
                "switchTouchMode": false,
                "switchMouseMode": false,
                "input": false,
                "quickInput": false,
                "outputText": "",
                "outputKeycodes": [],
                "bindViewGroup": []
              },
              "clickEvent": {
                "autoKeep": false,
                "autoClick": false,
                "openMenu": false,
                "switchTouchMode": false,
                "switchMouseMode": false,
                "input": false,
                "quickInput": false,
                "outputText": "",
                "outputKeycodes": [],
                "bindViewGroup": []
              },
              "doubleClickEvent": {
                "autoKeep": false,
                "autoClick": false,
                "openMenu": false,
                "switchTouchMode": false,
                "switchMouseMode": false,
                "input": false,
                "quickInput": false,
                "outputText": "",
                "outputKeycodes": [],
                "bindViewGroup": []
              }
            }
          },
          {
            "id": "641a2497-1c02-4a71-b361-69285c75c222",
            "text": "F5",
            "style": "HY://Pojav/normal",
            "baseInfo": {
              "visibilityType": "ALWAYS",
              "xPosition": 312,
              "yPosition": 8,
              "sizeType": "PERCENTAGE",
              "absoluteWidth": 50,
              "absoluteHeight": 50,
              "percentageWidth": {
                "reference": "SCREEN_HEIGHT",
                "size": 190
              },
              "percentageHeight": {
                "reference": "SCREEN_HEIGHT",
                "size": 80
              }
            },
            "event": {
              "pointerFollow": false,
              "Movable": false,
              "pressEvent": {
                "autoKeep": false,
                "autoClick": false,
                "openMenu": false,
                "switchTouchMode": false,
                "switchMouseMode": false,
                "input": false,
                "quickInput": false,
                "outputText": "",
                "outputKeycodes": [
                  63
                ],
                "bindViewGroup": []
              },
              "longPressEvent": {
                "autoKeep": false,
                "autoClick": false,
                "openMenu": false,
                "switchTouchMode": false,
                "switchMouseMode": false,
                "input": false,
                "quickInput": false,
                "outputText": "",
                "outputKeycodes": [],
                "bindViewGroup": []
              },
              "clickEvent": {
                "autoKeep": false,
                "autoClick": false,
                "openMenu": false,
                "switchTouchMode": false,
                "switchMouseMode": false,
                "input": false,
                "quickInput": false,
                "outputText": "",
                "outputKeycodes": [],
                "bindViewGroup": []
              },
              "doubleClickEvent": {
                "autoKeep": false,
                "autoClick": false,
                "openMenu": false,
                "switchTouchMode": false,
                "switchMouseMode": false,
                "input": false,
                "quickInput": false,
                "outputText": "",
                "outputKeycodes": [],
                "bindViewGroup": []
              }
            }
          },
          {
            "id": "d4f714c8-3f28-4a11-948e-f06676480ab0",
            "text": "T",
            "style": "HY://Pojav/normal",
            "baseInfo": {
              "visibilityType": "ALWAYS",
              "xPosition": 470,
              "yPosition": 8,
              "sizeType": "PERCENTAGE",
              "absoluteWidth": 50,
              "absoluteHeight": 50,
              "percentageWidth": {
                "reference": "SCREEN_HEIGHT",
                "size": 190
              },
              "percentageHeight": {
                "reference": "SCREEN_HEIGHT",
                "size": 80
              }
            },
            "event": {
              "pointerFollow": false,
              "Movable": false,
              "pressEvent": {
                "autoKeep": false,
                "autoClick": false,
                "openMenu": false,
                "switchTouchMode": false,
                "switchMouseMode": false,
                "input": false,
                "quickInput": false,
                "outputText": "",
                "outputKeycodes": [
                  20
                ],
                "bindViewGroup": []
              },
              "longPressEvent": {
                "autoKeep": false,
                "autoClick": false,
                "openMenu": false,
                "switchTouchMode": false,
                "switchMouseMode": false,
                "input": false,
                "quickInput": false,
                "outputText": "",
                "outputKeycodes": [],
                "bindViewGroup": []
              },
              "clickEvent": {
                "autoKeep": false,
                "autoClick": false,
                "openMenu": false,
                "switchTouchMode": false,
                "switchMouseMode": false,
                "input": false,
                "quickInput": false,
                "outputText": "",
                "outputKeycodes": [],
                "bindViewGroup": []
              },
              "doubleClickEvent": {
                "autoKeep": false,
                "autoClick": false,
                "openMenu": false,
                "switchTouchMode": false,
                "switchMouseMode": false,
                "input": false,
                "quickInput": false,
                "outputText": "",
                "outputKeycodes": [],
                "bindViewGroup": []
              }
            }
          },
          {
            "id": "566002c7-aebe-4e23-bd6c-dcf73ff846e0",
            "text": "Tab",
            "style": "HY://Pojav/normal",
            "baseInfo": {
              "visibilityType": "ALWAYS",
              "xPosition": 570,
              "yPosition": 8,
              "sizeType": "PERCENTAGE",
              "absoluteWidth": 50,
              "absoluteHeight": 50,
              "percentageWidth": {
                "reference": "SCREEN_HEIGHT",
                "size": 190
              },
              "percentageHeight": {
                "reference": "SCREEN_HEIGHT",
                "size": 80
              }
            },
            "event": {
              "pointerFollow": false,
              "Movable": false,
              "pressEvent": {
                "autoKeep": false,
                "autoClick": false,
                "openMenu": false,
                "switchTouchMode": false,
                "switchMouseMode": false,
                "input": false,
                "quickInput": false,
                "outputText": "",
                "outputKeycodes": [
                  15
                ],
                "bindViewGroup": []
              },
              "longPressEvent": {
                "autoKeep": false,
                "autoClick": false,
                "openMenu": false,
                "switchTouchMode": false,
                "switchMouseMode": false,
                "input": false,
                "quickInput": false,
                "outputText": "",
                "outputKeycodes": [],
                "bindViewGroup": []
              },
              "clickEvent": {
                "autoKeep": false,
                "autoClick": false,
                "openMenu": false,
                "switchTouchMode": false,
                "switchMouseMode": false,
                "input": false,
                "quickInput": false,
                "outputText": "",
                "outputKeycodes": [
                  15
                ],
                "bindViewGroup": []
              },
              "doubleClickEvent": {
                "autoKeep": false,
                "autoClick": false,
                "openMenu": false,
                "switchTouchMode": false,
                "switchMouseMode": false,
                "input": false,
                "quickInput": false,
                "outputText": "",
                "outputKeycodes": [],
                "bindViewGroup": []
              }
            }
          },
          {
            "id": "d82fbc24-633b-4db8-a5a8-b85b7e0ab4c6",
            "text": "Enter",
            "style": "HY://Pojav/normal",
            "baseInfo": {
              "visibilityType": "ALWAYS",
              "xPosition": 670,
              "yPosition": 8,
              "sizeType": "PERCENTAGE",
              "absoluteWidth": 50,
              "absoluteHeight": 50,
              "percentageWidth": {
                "reference": "SCREEN_HEIGHT",
                "size": 190
              },
              "percentageHeight": {
                "reference": "SCREEN_HEIGHT",
                "size": 80
              }
            },
            "event": {
              "pointerFollow": false,
              "Movable": false,
              "pressEvent": {
                "autoKeep": false,
                "autoClick": false,
                "openMenu": false,
                "switchTouchMode": false,
                "switchMouseMode": false,
                "input": false,
                "quickInput": false,
                "outputText": "",
                "outputKeycodes": [
                  28
                ],
                "bindViewGroup": []
              },
              "longPressEvent": {
                "autoKeep": false,
                "autoClick": false,
                "openMenu": false,
                "switchTouchMode": false,
                "switchMouseMode": false,
                "input": false,
                "quickInput": false,
                "outputText": "",
                "outputKeycodes": [],
                "bindViewGroup": []
              },
              "clickEvent": {
                "autoKeep": false,
                "autoClick": false,
                "openMenu": false,
                "switchTouchMode": false,
                "switchMouseMode": false,
                "input": false,
                "quickInput": false,
                "outputText": "",
                "outputKeycodes": [
                  15
                ],
                "bindViewGroup": []
              },
              "doubleClickEvent": {
                "autoKeep": false,
                "autoClick": false,
                "openMenu": false,
                "switchTouchMode": false,
                "switchMouseMode": false,
                "input": false,
                "quickInput": false,
                "outputText": "",
                "outputKeycodes": [],
                "bindViewGroup": []
              }
            }
          },
          {
            "id": "1d422200-ab8b-44b6-9f49-c94912b5dbcd",
            "text": "键盘",
            "style": "HY://Pojav/normal",
            "baseInfo": {
              "visibilityType": "ALWAYS",
              "xPosition": 890,
              "yPosition": 8,
              "sizeType": "PERCENTAGE",
              "absoluteWidth": 50,
              "absoluteHeight": 50,
              "percentageWidth": {
                "reference": "SCREEN_HEIGHT",
                "size": 190
              },
              "percentageHeight": {
                "reference": "SCREEN_HEIGHT",
                "size": 80
              }
            },
            "event": {
              "pointerFollow": false,
              "Movable": false,
              "pressEvent": {
                "autoKeep": false,
                "autoClick": false,
                "openMenu": false,
                "switchTouchMode": false,
                "switchMouseMode": false,
                "input": true,
                "quickInput": false,
                "outputText": "",
                "outputKeycodes": [],
                "bindViewGroup": []
              },
              "longPressEvent": {
                "autoKeep": false,
                "autoClick": false,
                "openMenu": false,
                "switchTouchMode": false,
                "switchMouseMode": false,
                "input": false,
                "quickInput": false,
                "outputText": "",
                "outputKeycodes": [],
                "bindViewGroup": []
              },
              "clickEvent": {
                "autoKeep": false,
                "autoClick": false,
                "openMenu": false,
                "switchTouchMode": false,
                "switchMouseMode": false,
                "input": false,
                "quickInput": false,
                "outputText": "",
                "outputKeycodes": [],
                "bindViewGroup": []
              },
              "doubleClickEvent": {
                "autoKeep": false,
                "autoClick": false,
                "openMenu": false,
                "switchTouchMode": false,
                "switchMouseMode": false,
                "input": false,
                "quickInput": false,
                "outputText": "",
                "outputKeycodes": [],
                "bindViewGroup": []
              }
            }
          },
          {
            "id": "0fd28cda-ec3c-404d-8061-ef20c89252c5",
            "text": "◆",
            "style": "HY://Pojav/normal",
            "baseInfo": {
              "visibilityType": "ALWAYS",
              "xPosition": 106,
              "yPosition": 728,
              "sizeType": "PERCENTAGE",
              "absoluteWidth": 50,
              "absoluteHeight": 50,
              "percentageWidth": {
                "reference": "SCREEN_HEIGHT",
                "size": 130
              },
              "percentageHeight": {
                "reference": "SCREEN_HEIGHT",
                "size": 130
              }
            },
            "event": {
              "pointerFollow": false,
              "Movable": false,
              "pressEvent": {
                "autoKeep": true,
                "autoClick": false,
                "openMenu": false,
                "switchTouchMode": false,
                "switchMouseMode": false,
                "input": false,
                "quickInput": false,
                "outputText": "",
                "outputKeycodes": [
                  42
                ],
                "bindViewGroup": []
              },
              "longPressEvent": {
                "autoKeep": false,
                "autoClick": false,
                "openMenu": false,
                "switchTouchMode": false,
                "switchMouseMode": false,
                "input": false,
                "quickInput": false,
                "outputText": "",
                "outputKeycodes": [],
                "bindViewGroup": []
              },
              "clickEvent": {
                "autoKeep": false,
                "autoClick": false,
                "openMenu": false,
                "switchTouchMode": false,
                "switchMouseMode": false,
                "input": false,
                "quickInput": false,
                "outputText": "",
                "outputKeycodes": [],
                "bindViewGroup": []
              },
              "doubleClickEvent": {
                "autoKeep": false,
                "autoClick": false,
                "openMenu": false,
                "switchTouchMode": false,
                "switchMouseMode": false,
                "input": false,
                "quickInput": false,
                "outputText": "",
                "outputKeycodes": [],
                "bindViewGroup": []
              }
            }
          },
          {
            "id": "83d6994c-5bcc-41cf-8e79-0c723892170f",
            "text": "▲",
            "style": "HY://Pojav/normal",
            "baseInfo": {
              "visibilityType": "ALWAYS",
              "xPosition": 106,
              "yPosition": 552,
              "sizeType": "PERCENTAGE",
              "absoluteWidth": 50,
              "absoluteHeight": 50,
              "percentageWidth": {
                "reference": "SCREEN_HEIGHT",
                "size": 130
              },
              "percentageHeight": {
                "reference": "SCREEN_HEIGHT",
                "size": 130
              }
            },
            "event": {
              "pointerFollow": false,
              "Movable": false,
              "pressEvent": {
                "autoKeep": false,
                "autoClick": false,
                "openMenu": false,
                "switchTouchMode": false,
                "switchMouseMode": false,
                "input": false,
                "quickInput": false,
                "outputText": "",
                "outputKeycodes": [
                  17
                ],
                "bindViewGroup": []
              },
              "longPressEvent": {
                "autoKeep": false,
                "autoClick": false,
                "openMenu": false,
                "switchTouchMode": false,
                "switchMouseMode": false,
                "input": false,
                "quickInput": false,
                "outputText": "",
                "outputKeycodes": [],
                "bindViewGroup": []
              },
              "clickEvent": {
                "autoKeep": false,
                "autoClick": false,
                "openMenu": false,
                "switchTouchMode": false,
                "switchMouseMode": false,
                "input": false,
                "quickInput": false,
                "outputText": "",
                "outputKeycodes": [],
                "bindViewGroup": []
              },
              "doubleClickEvent": {
                "autoKeep": false,
                "autoClick": false,
                "openMenu": false,
                "switchTouchMode": false,
                "switchMouseMode": false,
                "input": false,
                "quickInput": false,
                "outputText": "",
                "outputKeycodes": [],
                "bindViewGroup": []
              }
            }
          },
          {
            "id": "40c514b7-4316-4014-9f68-d9cfcb82a55d",
            "text": "▼",
            "style": "HY://Pojav/normal",
            "baseInfo": {
              "visibilityType": "ALWAYS",
              "xPosition": 106,
              "yPosition": 904,
              "sizeType": "PERCENTAGE",
              "absoluteWidth": 50,
              "absoluteHeight": 50,
              "percentageWidth": {
                "reference": "SCREEN_HEIGHT",
                "size": 130
              },
              "percentageHeight": {
                "reference": "SCREEN_HEIGHT",
                "size": 130
              }
            },
            "event": {
              "pointerFollow": false,
              "Movable": false,
              "pressEvent": {
                "autoKeep": false,
                "autoClick": false,
                "openMenu": false,
                "switchTouchMode": false,
                "switchMouseMode": false,
                "input": false,
                "quickInput": false,
                "outputText": "",
                "outputKeycodes": [
                  31
                ],
                "bindViewGroup": []
              },
              "longPressEvent": {
                "autoKeep": false,
                "autoClick": false,
                "openMenu": false,
                "switchTouchMode": false,
                "switchMouseMode": false,
                "input": false,
                "quickInput": false,
                "outputText": "",
                "outputKeycodes": [],
                "bindViewGroup": []
              },
              "clickEvent": {
                "autoKeep": false,
                "autoClick": false,
                "openMenu": false,
                "switchTouchMode": false,
                "switchMouseMode": false,
                "input": false,
                "quickInput": false,
                "outputText": "",
                "outputKeycodes": [],
                "bindViewGroup": []
              },
              "doubleClickEvent": {
                "autoKeep": false,
                "autoClick": false,
                "openMenu": false,
                "switchTouchMode": false,
                "switchMouseMode": false,
                "input": false,
                "quickInput": false,
                "outputText": "",
                "outputKeycodes": [],
                "bindViewGroup": []
              }
            }
          },
          {
            "id": "86493505-176b-494f-95f2-0ac24ac6c577",
            "text": "◀",
            "style": "HY://Pojav/normal",
            "baseInfo": {
              "visibilityType": "ALWAYS",
              "xPosition": 28,
              "yPosition": 728,
              "sizeType": "PERCENTAGE",
              "absoluteWidth": 50,
              "absoluteHeight": 50,
              "percentageWidth": {
                "reference": "SCREEN_HEIGHT",
                "size": 130
              },
              "percentageHeight": {
                "reference": "SCREEN_HEIGHT",
                "size": 130
              }
            },
            "event": {
              "pointerFollow": false,
              "Movable": false,
              "pressEvent": {
                "autoKeep": false,
                "autoClick": false,
                "openMenu": false,
                "switchTouchMode": false,
                "switchMouseMode": false,
                "input": false,
                "quickInput": false,
                "outputText": "",
                "outputKeycodes": [
                  30
                ],
                "bindViewGroup": []
              },
              "longPressEvent": {
                "autoKeep": false,
                "autoClick": false,
                "openMenu": false,
                "switchTouchMode": false,
                "switchMouseMode": false,
                "input": false,
                "quickInput": false,
                "outputText": "",
                "outputKeycodes": [],
                "bindViewGroup": []
              },
              "clickEvent": {
                "autoKeep": false,
                "autoClick": false,
                "openMenu": false,
                "switchTouchMode": false,
                "switchMouseMode": false,
                "input": false,
                "quickInput": false,
                "outputText": "",
                "outputKeycodes": [],
                "bindViewGroup": []
              },
              "doubleClickEvent": {
                "autoKeep": false,
                "autoClick": false,
                "openMenu": false,
                "switchTouchMode": false,
                "switchMouseMode": false,
                "input": false,
                "quickInput": false,
                "outputText": "",
                "outputKeycodes": [],
                "bindViewGroup": []
              }
            }
          },
          {
            "id": "1d734362-bdab-47b2-bdb0-b65a025a840e",
            "text": "▶",
            "style": "HY://Pojav/normal",
            "baseInfo": {
              "visibilityType": "ALWAYS",
              "xPosition": 184,
              "yPosition": 728,
              "sizeType": "PERCENTAGE",
              "absoluteWidth": 50,
              "absoluteHeight": 50,
              "percentageWidth": {
                "reference": "SCREEN_HEIGHT",
                "size": 130
              },
              "percentageHeight": {
                "reference": "SCREEN_HEIGHT",
                "size": 130
              }
            },
            "event": {
              "pointerFollow": false,
              "Movable": false,
              "pressEvent": {
                "autoKeep": false,
                "autoClick": false,
                "openMenu": false,
                "switchTouchMode": false,
                "switchMouseMode": false,
                "input": false,
                "quickInput": false,
                "outputText": "",
                "outputKeycodes": [
                  32
                ],
                "bindViewGroup": []
              },
              "longPressEvent": {
                "autoKeep": false,
                "autoClick": false,
                "openMenu": false,
                "switchTouchMode": false,
                "switchMouseMode": false,
                "input": false,
                "quickInput": false,
                "outputText": "",
                "outputKeycodes": [],
                "bindViewGroup": []
              },
              "clickEvent": {
                "autoKeep": false,
                "autoClick": false,
                "openMenu": false,
                "switchTouchMode": false,
                "switchMouseMode": false,
                "input": false,
                "quickInput": false,
                "outputText": "",
                "outputKeycodes": [],
                "bindViewGroup": []
              },
              "doubleClickEvent": {
                "autoKeep": false,
                "autoClick": false,
                "openMenu": false,
                "switchTouchMode": false,
                "switchMouseMode": false,
                "input": false,
                "quickInput": false,
                "outputText": "",
                "outputKeycodes": [],
                "bindViewGroup": []
              }
            }
          },
          {
            "id": "1725ecf9-4579-43bc-a6f9-ab02d7cc31f7",
            "text": "↖",
            "style": "HY://Pojav/normal",
            "baseInfo": {
              "visibilityType": "ALWAYS",
              "xPosition": 38,
              "yPosition": 574,
              "sizeType": "PERCENTAGE",
              "absoluteWidth": 50,
              "absoluteHeight": 50,
              "percentageWidth": {
                "reference": "SCREEN_HEIGHT",
                "size": 130
              },
              "percentageHeight": {
                "reference": "SCREEN_HEIGHT",
                "size": 130
              }
            },
            "event": {
              "pointerFollow": false,
              "Movable": false,
              "pressEvent": {
                "autoKeep": false,
                "autoClick": false,
                "openMenu": false,
                "switchTouchMode": false,
                "switchMouseMode": false,
                "input": false,
                "quickInput": false,
                "outputText": "",
                "outputKeycodes": [
                  17,
                  30
                ],
                "bindViewGroup": []
              },
              "longPressEvent": {
                "autoKeep": false,
                "autoClick": false,
                "openMenu": false,
                "switchTouchMode": false,
                "switchMouseMode": false,
                "input": false,
                "quickInput": false,
                "outputText": "",
                "outputKeycodes": [],
                "bindViewGroup": []
              },
              "clickEvent": {
                "autoKeep": false,
                "autoClick": false,
                "openMenu": false,
                "switchTouchMode": false,
                "switchMouseMode": false,
                "input": false,
                "quickInput": false,
                "outputText": "",
                "outputKeycodes": [],
                "bindViewGroup": []
              },
              "doubleClickEvent": {
                "autoKeep": false,
                "autoClick": false,
                "openMenu": false,
                "switchTouchMode": false,
                "switchMouseMode": false,
                "input": false,
                "quickInput": false,
                "outputText": "",
                "outputKeycodes": [],
                "bindViewGroup": []
              }
            }
          },
          {
            "id": "568d7a99-6455-4502-b612-f340dba0a260",
            "text": "↗",
            "style": "HY://Pojav/normal",
            "baseInfo": {
              "visibilityType": "ALWAYS",
              "xPosition": 173,
              "yPosition": 574,
              "sizeType": "PERCENTAGE",
              "absoluteWidth": 50,
              "absoluteHeight": 50,
              "percentageWidth": {
                "reference": "SCREEN_HEIGHT",
                "size": 130
              },
              "percentageHeight": {
                "reference": "SCREEN_HEIGHT",
                "size": 130
              }
            },
            "event": {
              "pointerFollow": false,
              "Movable": false,
              "pressEvent": {
                "autoKeep": false,
                "autoClick": false,
                "openMenu": false,
                "switchTouchMode": false,
                "switchMouseMode": false,
                "input": false,
                "quickInput": false,
                "outputText": "",
                "outputKeycodes": [
                  17,
                  32
                ],
                "bindViewGroup": []
              },
              "longPressEvent": {
                "autoKeep": false,
                "autoClick": false,
                "openMenu": false,
                "switchTouchMode": false,
                "switchMouseMode": false,
                "input": false,
                "quickInput": false,
                "outputText": "",
                "outputKeycodes": [],
                "bindViewGroup": []
              },
              "clickEvent": {
                "autoKeep": false,
                "autoClick": false,
                "openMenu": false,
                "switchTouchMode": false,
                "switchMouseMode": false,
                "input": false,
                "quickInput": false,
                "outputText": "",
                "outputKeycodes": [],
                "bindViewGroup": []
              },
              "doubleClickEvent": {
                "autoKeep": false,
                "autoClick": false,
                "openMenu": false,
                "switchTouchMode": false,
                "switchMouseMode": false,
                "input": false,
                "quickInput": false,
                "outputText": "",
                "outputKeycodes": [],
                "bindViewGroup": []
              }
            }
          },
          {
            "id": "661a2689-4731-4d49-8bf2-3062310d2870",
            "text": "↙",
            "style": "HY://Pojav/normal",
            "baseInfo": {
              "visibilityType": "ALWAYS",
              "xPosition": 38,
              "yPosition": 882,
              "sizeType": "PERCENTAGE",
              "absoluteWidth": 50,
              "absoluteHeight": 50,
              "percentageWidth": {
                "reference": "SCREEN_HEIGHT",
                "size": 130
              },
              "percentageHeight": {
                "reference": "SCREEN_HEIGHT",
                "size": 130
              }
            },
            "event": {
              "pointerFollow": false,
              "Movable": false,
              "pressEvent": {
                "autoKeep": false,
                "autoClick": false,
                "openMenu": false,
                "switchTouchMode": false,
                "switchMouseMode": false,
                "input": false,
                "quickInput": false,
                "outputText": "",
                "outputKeycodes": [
                  31,
                  30
                ],
                "bindViewGroup": []
              },
              "longPressEvent": {
                "autoKeep": false,
                "autoClick": false,
                "openMenu": false,
                "switchTouchMode": false,
                "switchMouseMode": false,
                "input": false,
                "quickInput": false,
                "outputText": "",
                "outputKeycodes": [],
                "bindViewGroup": []
              },
              "clickEvent": {
                "autoKeep": false,
                "autoClick": false,
                "openMenu": false,
                "switchTouchMode": false,
                "switchMouseMode": false,
                "input": false,
                "quickInput": false,
                "outputText": "",
                "outputKeycodes": [],
                "bindViewGroup": []
              },
              "doubleClickEvent": {
                "autoKeep": false,
                "autoClick": false,
                "openMenu": false,
                "switchTouchMode": false,
                "switchMouseMode": false,
                "input": false,
                "quickInput": false,
                "outputText": "",
                "outputKeycodes": [],
                "bindViewGroup": []
              }
            }
          },
          {
            "id": "52dea39c-c477-41b6-96ee-b52a6b527c4e",
            "text": "↘",
            "style": "HY://Pojav/normal",
            "baseInfo": {
              "visibilityType": "ALWAYS",
              "xPosition": 173,
              "yPosition": 882,
              "sizeType": "PERCENTAGE",
              "absoluteWidth": 50,
              "absoluteHeight": 50,
              "percentageWidth": {
                "reference": "SCREEN_HEIGHT",
                "size": 130
              },
              "percentageHeight": {
                "reference": "SCREEN_HEIGHT",
                "size": 130
              }
            },
            "event": {
              "pointerFollow": false,
              "Movable": false,
              "pressEvent": {
                "autoKeep": false,
                "autoClick": false,
                "openMenu": false,
                "switchTouchMode": false,
                "switchMouseMode": false,
                "input": false,
                "quickInput": false,
                "outputText": "",
                "outputKeycodes": [
                  31,
                  32
                ],
                "bindViewGroup": []
              },
              "longPressEvent": {
                "autoKeep": false,
                "autoClick": false,
                "openMenu": false,
                "switchTouchMode": false,
                "switchMouseMode": false,
                "input": false,
                "quickInput": false,
                "outputText": "",
                "outputKeycodes": [],
                "bindViewGroup": []
              },
              "clickEvent": {
                "autoKeep": false,
                "autoClick": false,
                "openMenu": false,
                "switchTouchMode": false,
                "switchMouseMode": false,
                "input": false,
                "quickInput": false,
                "outputText": "",
                "outputKeycodes": [],
                "bindViewGroup": []
              },
              "doubleClickEvent": {
                "autoKeep": false,
                "autoClick": false,
                "openMenu": false,
                "switchTouchMode": false,
                "switchMouseMode": false,
                "input": false,
                "quickInput": false,
                "outputText": "",
                "outputKeycodes": [],
                "bindViewGroup": []
              }
            }
          },
          {
            "id": "2c1ef96c-5f4f-4861-85c6-94939b92cf17",
            "text": "×",
            "style": "HY://Pojav/normal",
            "baseInfo": {
              "visibilityType": "ALWAYS",
              "xPosition": 778,
              "yPosition": 709,
              "sizeType": "PERCENTAGE",
              "absoluteWidth": 50,
              "absoluteHeight": 50,
              "percentageWidth": {
                "reference": "SCREEN_HEIGHT",
                "size": 130
              },
              "percentageHeight": {
                "reference": "SCREEN_HEIGHT",
                "size": 130
              }
            },
            "event": {
              "pointerFollow": false,
              "Movable": false,
              "pressEvent": {
                "autoKeep": false,
                "autoClick": false,
                "openMenu": false,
                "switchTouchMode": false,
                "switchMouseMode": false,
                "input": false,
                "quickInput": false,
                "outputText": "",
                "outputKeycodes": [
                  1000
                ],
                "bindViewGroup": []
              },
              "longPressEvent": {
                "autoKeep": false,
                "autoClick": false,
                "openMenu": false,
                "switchTouchMode": false,
                "switchMouseMode": false,
                "input": false,
                "quickInput": false,
                "outputText": "",
                "outputKeycodes": [],
                "bindViewGroup": []
              },
              "clickEvent": {
                "autoKeep": false,
                "autoClick": false,
                "openMenu": false,
                "switchTouchMode": false,
                "switchMouseMode": false,
                "input": false,
                "quickInput": false,
                "outputText": "",
                "outputKeycodes": [],
                "bindViewGroup": []
              },
              "doubleClickEvent": {
                "autoKeep": false,
                "autoClick": false,
                "openMenu": false,
                "switchTouchMode": false,
                "switchMouseMode": false,
                "input": false,
                "quickInput": false,
                "outputText": "",
                "outputKeycodes": [],
                "bindViewGroup": []
              }
            }
          },
          {
            "id": "9b78d937-d9f8-4483-b3c5-5bc5ec854629",
            "text": "○",
            "style": "HY://Pojav/normal",
            "baseInfo": {
              "visibilityType": "ALWAYS",
              "xPosition": 855,
              "yPosition": 535,
              "sizeType": "PERCENTAGE",
              "absoluteWidth": 50,
              "absoluteHeight": 50,
              "percentageWidth": {
                "reference": "SCREEN_HEIGHT",
                "size": 130
              },
              "percentageHeight": {
                "reference": "SCREEN_HEIGHT",
                "size": 130
              }
            },
            "event": {
              "pointerFollow": false,
              "Movable": false,
              "pressEvent": {
                "autoKeep": false,
                "autoClick": false,
                "openMenu": false,
                "switchTouchMode": false,
                "switchMouseMode": false,
                "input": false,
                "quickInput": false,
                "outputText": "",
                "outputKeycodes": [
                  1002
                ],
                "bindViewGroup": []
              },
              "longPressEvent": {
                "autoKeep": false,
                "autoClick": false,
                "openMenu": false,
                "switchTouchMode": false,
                "switchMouseMode": false,
                "input": false,
                "quickInput": false,
                "outputText": "",
                "outputKeycodes": [],
                "bindViewGroup": []
              },
              "clickEvent": {
                "autoKeep": false,
                "autoClick": false,
                "openMenu": false,
                "switchTouchMode": false,
                "switchMouseMode": false,
                "input": false,
                "quickInput": false,
                "outputText": "",
                "outputKeycodes": [],
                "bindViewGroup": []
              },
              "doubleClickEvent": {
                "autoKeep": false,
                "autoClick": false,
                "openMenu": false,
                "switchTouchMode": false,
                "switchMouseMode": false,
                "input": false,
                "quickInput": false,
                "outputText": "",
                "outputKeycodes": [],
                "bindViewGroup": []
              }
            }
          },
          {
            "id": "24fa1fb9-f8e7-4bdc-9132-4e0384ada6a2",
            "text": "⬛",
            "style": "HY://Pojav/normal",
            "baseInfo": {
              "visibilityType": "ALWAYS",
              "xPosition": 855,
              "yPosition": 709,
              "sizeType": "PERCENTAGE",
              "absoluteWidth": 50,
              "absoluteHeight": 50,
              "percentageWidth": {
                "reference": "SCREEN_HEIGHT",
                "size": 130
              },
              "percentageHeight": {
                "reference": "SCREEN_HEIGHT",
                "size": 130
              }
            },
            "event": {
              "pointerFollow": false,
              "Movable": false,
              "pressEvent": {
                "autoKeep": false,
                "autoClick": false,
                "openMenu": false,
                "switchTouchMode": false,
                "switchMouseMode": false,
                "input": false,
                "quickInput": false,
                "outputText": "",
                "outputKeycodes": [
                  57
                ],
                "bindViewGroup": []
              },
              "longPressEvent": {
                "autoKeep": false,
                "autoClick": false,
                "openMenu": false,
                "switchTouchMode": false,
                "switchMouseMode": false,
                "input": false,
                "quickInput": false,
                "outputText": "",
                "outputKeycodes": [],
                "bindViewGroup": []
              },
              "clickEvent": {
                "autoKeep": false,
                "autoClick": false,
                "openMenu": false,
                "switchTouchMode": false,
                "switchMouseMode": false,
                "input": false,
                "quickInput": false,
                "outputText": "",
                "outputKeycodes": [],
                "bindViewGroup": []
              },
              "doubleClickEvent": {
                "autoKeep": false,
                "autoClick": false,
                "openMenu": false,
                "switchTouchMode": false,
                "switchMouseMode": false,
                "input": false,
                "quickInput": false,
                "outputText": "",
                "outputKeycodes": [],
                "bindViewGroup": []
              }
            }
          },
          {
            "id": "a2800363-61ec-4337-9086-9146f5ba9e73",
            "text": "E",
            "style": "HY://Pojav/normal",
            "baseInfo": {
              "visibilityType": "ALWAYS",
              "xPosition": 727,
              "yPosition": 974,
              "sizeType": "PERCENTAGE",
              "absoluteWidth": 50,
              "absoluteHeight": 50,
              "percentageWidth": {
                "reference": "SCREEN_HEIGHT",
                "size": 130
              },
              "percentageHeight": {
                "reference": "SCREEN_HEIGHT",
                "size": 130
              }
            },
            "event": {
              "pointerFollow": false,
              "Movable": false,
              "pressEvent": {
                "autoKeep": false,
                "autoClick": false,
                "openMenu": false,
                "switchTouchMode": false,
                "switchMouseMode": false,
                "input": false,
                "quickInput": false,
                "outputText": "",
                "outputKeycodes": [
                  18
                ],
                "bindViewGroup": []
              },
              "longPressEvent": {
                "autoKeep": false,
                "autoClick": false,
                "openMenu": false,
                "switchTouchMode": false,
                "switchMouseMode": false,
                "input": false,
                "quickInput": false,
                "outputText": "",
                "outputKeycodes": [],
                "bindViewGroup": []
              },
              "clickEvent": {
                "autoKeep": false,
                "autoClick": false,
                "openMenu": false,
                "switchTouchMode": false,
                "switchMouseMode": false,
                "input": false,
                "quickInput": false,
                "outputText": "",
                "outputKeycodes": [],
                "bindViewGroup": []
              },
              "doubleClickEvent": {
                "autoKeep": false,
                "autoClick": false,
                "openMenu": false,
                "switchTouchMode": false,
                "switchMouseMode": false,
                "input": false,
                "quickInput": false,
                "outputText": "",
                "outputKeycodes": [],
                "bindViewGroup": []
              }
            }
          }
        ],
        "directionList": []
      }
    },
    {
      "id": "a8f2d464-3cf2-4f2c-893f-bb5e20f944a3",
      "name": "_SPECIAL",
      "visibility": "VISIBLE",
      "viewData": {
        "buttonList": [
          {
            "id": "14561ed5-73e2-461d-96ee-8d00891fa70a",
            "text": "GUI",
            "style": "HY://Pojav/normal",
            "baseInfo": {
              "visibilityType": "ALWAYS",
              "xPosition": 990,
              "yPosition": 990,
              "sizeType": "PERCENTAGE",
              "absoluteWidth": 50,
              "absoluteHeight": 50,
              "percentageWidth": {
                "reference": "SCREEN_HEIGHT",
                "size": 130
              },
              "percentageHeight": {
                "reference": "SCREEN_HEIGHT",
                "size": 130
              }
            },
            "event": {
              "pointerFollow": false,
              "Movable": false,
              "pressEvent": {
                "autoKeep": false,
                "autoClick": false,
                "openMenu": false,
                "switchTouchMode": false,
                "switchMouseMode": false,
                "input": false,
                "quickInput": false,
                "outputText": "",
                "outputKeycodes": [],
                "bindViewGroup": [
                  "f5c607a6-da93-44a7-8ebc-ee75449eae58"
                ]
              },
              "longPressEvent": {
                "autoKeep": false,
                "autoClick": false,
                "openMenu": false,
                "switchTouchMode": false,
                "switchMouseMode": false,
                "input": false,
                "quickInput": false,
                "outputText": "",
                "outputKeycodes": [],
                "bindViewGroup": []
              },
              "clickEvent": {
                "autoKeep": false,
                "autoClick": false,
                "openMenu": false,
                "switchTouchMode": false,
                "switchMouseMode": false,
                "input": false,
                "quickInput": false,
                "outputText": "",
                "outputKeycodes": [],
                "bindViewGroup": []
              },
              "doubleClickEvent": {
                "autoKeep": false,
                "autoClick": false,
                "openMenu": false,
                "switchTouchMode": false,
                "switchMouseMode": false,
                "input": false,
                "quickInput": false,
                "outputText": "",
                "outputKeycodes": [],
                "bindViewGroup": []
              }
            }
          },
          {
            "id": "46ed54c9-7fe6-4bd2-9df6-0725cbbe966a",
            "text": "Mouse",
            "style": "HY://Pojav/normal",
            "baseInfo": {
              "visibilityType": "ALWAYS",
              "xPosition": 990,
              "yPosition": 8,
              "sizeType": "PERCENTAGE",
              "absoluteWidth": 50,
              "absoluteHeight": 50,
              "percentageWidth": {
                "reference": "SCREEN_HEIGHT",
                "size": 190
              },
              "percentageHeight": {
                "reference": "SCREEN_HEIGHT",
                "size": 80
              }
            },
            "event": {
              "pointerFollow": false,
              "Movable": false,
              "pressEvent": {
                "autoKeep": false,
                "autoClick": false,
                "openMenu": false,
                "switchTouchMode": false,
                "switchMouseMode": true,
                "input": false,
                "quickInput": false,
                "outputText": "",
                "outputKeycodes": [],
                "bindViewGroup": []
              },
              "longPressEvent": {
                "autoKeep": false,
                "autoClick": false,
                "openMenu": false,
                "switchTouchMode": false,
                "switchMouseMode": false,
                "input": false,
                "quickInput": false,
                "outputText": "",
                "outputKeycodes": [],
                "bindViewGroup": []
              },
              "clickEvent": {
                "autoKeep": false,
                "autoClick": false,
                "openMenu": false,
                "switchTouchMode": false,
                "switchMouseMode": false,
                "input": false,
                "quickInput": false,
                "outputText": "",
                "outputKeycodes": [],
                "bindViewGroup": []
              },
              "doubleClickEvent": {
                "autoKeep": false,
                "autoClick": false,
                "openMenu": false,
                "switchTouchMode": false,
                "switchMouseMode": false,
                "input": false,
                "quickInput": false,
                "outputText": "",
                "outputKeycodes": [],
                "bindViewGroup": []
              }
            }
          }
        ],
        "directionList": []
      }
    }
  ]
}